{"stat.chestOpened":2,"stat.walkOneCm":194872,"stat.playerKills":5,"achievement.openInventory":5,"stat.leaveGame":5,"stat.damageTaken":875,"stat.useItem.minecraft.diamond_sword":5,"stat.flyOneCm":1507317,"stat.useItem.minecraft.bedrock":4,"stat.jump":1329,"stat.swimOneCm":712,"stat.playOneMinute":98532,"stat.fallOneCm":20855,"stat.damageDealt":1445,"stat.crouchOneCm":265,"stat.timeSinceDeath":98532,"stat.useItem.minecraft.obsidian":1,"stat.sprintOneCm":134552,"achievement.exploreAllBiomes":{"value":0,"progress":["Plains"]}}